deep_code/__init__.py
deep_code/constants.py
deep_code/version.py
deep_code/cli/__init__.py
deep_code/cli/generate_config.py
deep_code/cli/main.py
deep_code/cli/publish.py
deep_code/tests/tools/__init__.py
deep_code/tests/tools/test_publish.py
deep_code/tests/utils/__init__.py
deep_code/tests/utils/test_custom_xrlint_rules.py
deep_code/tests/utils/test_dataset_stac_generator.py
deep_code/tests/utils/test_github_automation.py
deep_code/tests/utils/test_helper.py
deep_code/tests/utils/test_ogc_api_record.py
deep_code/tests/utils/test_ogc_record_generator.py
deep_code/tests/utils/test_osc_extension.py
deep_code/tools/__init__.py
deep_code/tools/lint.py
deep_code/tools/new.py
deep_code/tools/publish.py
deep_code/tools/register.py
deep_code/tools/setup_ci.py
deep_code/tools/test.py
deep_code/utils/__init__.py
deep_code/utils/custom_xrlint_rules.py
deep_code/utils/dataset_stac_generator.py
deep_code/utils/github_automation.py
deep_code/utils/helper.py
deep_code/utils/ogc_api_record.py
deep_code/utils/ogc_record_generator.py
deep_code/utils/osc_extension.py
deep_code-0.1.6.dist-info/licenses/LICENSE
deep_code-0.1.6.dist-info/METADATA
deep_code-0.1.6.dist-info/WHEEL
deep_code-0.1.6.dist-info/entry_points.txt
deep_code-0.1.6.dist-info/top_level.txt
deep_code-0.1.6.dist-info/RECORD
