Metadata-Version: 2.4
Name: deep_code
Version: 0.1.6
Summary: deepesdl earthcode integration utility tool
Author-email: Tejas Morbagal Harish <tejas.morbagalharish@brockmann-consult.de>
License: MIT
Project-URL: Repository, https://github.com/deepesdl/deep-code
Project-URL: Issues, https://github.com/deepesdl/deep-code/issues
Project-URL: Changelog, https://github.com/deepesdl/deep-code/blob/main/CHANGES.md
Keywords: analysis ready data,data science,datacube,xarray,zarr,xcube,stac,FAIR,reproducible workflow,DeepESDL
Requires-Python: >=3.10
License-File: LICENSE
Requires-Dist: click
Requires-Dist: fsspec
Requires-Dist: jsonschema
Requires-Dist: jsonpickle
Requires-Dist: requests
Requires-Dist: pandas
Requires-Dist: pystac
Requires-Dist: pyyaml
Requires-Dist: xcube-core
Requires-Dist: xrlint
Provides-Extra: dev
Requires-Dist: black; extra == "dev"
Requires-Dist: flake8; extra == "dev"
Requires-Dist: numpy; extra == "dev"
Requires-Dist: ruff; extra == "dev"
Requires-Dist: pytest; extra == "dev"
Requires-Dist: pytest-cov; extra == "dev"
Requires-Dist: pytest-recording; extra == "dev"
Dynamic: license-file
